infer_libs/__init__.py
infer_libs/audio.py
infer_libs/fcpe.py
infer_libs/rmvpe.py
infer_libs/infer_pack/__init__.py
infer_libs/infer_pack/attentions.py
infer_libs/infer_pack/commons.py
infer_libs/infer_pack/models.py
infer_libs/infer_pack/modules.py
infer_libs/infer_pack/transforms.py
Harmonify-0.1.0.dist-info/METADATA
Harmonify-0.1.0.dist-info/WHEEL
Harmonify-0.1.0.dist-info/top_level.txt
Harmonify-0.1.0.dist-info/RECORD
