Metadata-Version: 2.1
Name: Harmonify
Version: 0.1.0
Summary: Harmonify: A project fork of RVC V2
Home-page: https://github.com/Ryouko-Yamanda65777/Harmonify.git
Author: Ryouko Yamanda
Author-email: blane187git@gmail.com
Requires-Python: >=3.6
Requires-Dist: av
Requires-Dist: ffmpeg-python>=0.2.0
Requires-Dist: faiss-cpu==1.7.3
Requires-Dist: praat-parselmouth==0.4.2
Requires-Dist: pyworld==0.3.4
Requires-Dist: resampy==0.4.2
Requires-Dist: fairseq==0.12.2
Requires-Dist: pydub==0.25.1
Requires-Dist: einops
Requires-Dist: local-attention
Requires-Dist: torchcrepe==0.0.20
Requires-Dist: torchfcpe
Requires-Dist: gradio
Requires-Dist: yt-dlp
Requires-Dist: audio-separator[gpu]
